scrappy/__init__.py
scrappy/core/__init__.py
scrappy/core/commands.py
scrappy/core/crash_dump.py
scrappy/core/utils.py
scrappy/distributed/__init__.py
scrappy/distributed/agent/__init__.py
scrappy/distributed/agent/agent.py
scrappy/distributed/core/__init__.py
scrappy/distributed/core/crash_dump.py
scrappy/driver/__init__.py
scrappy/driver/pool.py
scrappy/driver/worker.py
scrappy/scheduler/__init__.py
scrappy/scheduler/round_robin.py
scrappy/scheduler/scheduler.py
scrappy/tasks/__init__.py
scrappy/tasks/sample_tasks.py
scrappy/tasks/simple_task.py
scrappy/tasks/task.py
scrappy/util/__init__.py
scrappy/util/tmpFile.py
scrappy_webdriver-0.0.2.dist-info/LICENSE
scrappy_webdriver-0.0.2.dist-info/METADATA
scrappy_webdriver-0.0.2.dist-info/WHEEL
scrappy_webdriver-0.0.2.dist-info/top_level.txt
scrappy_webdriver-0.0.2.dist-info/RECORD
